denopy-0.5.0.dist-info/METADATA
denopy-0.5.0.dist-info/WHEEL
denopy-0.5.0.dist-info/licenses/LICENSE
denopy/__init__.py
denopy/denopy.abi3.so
denopy-0.5.0.dist-info/RECORD
