Metadata-Version: 2.3
Name: denopy
Version: 0.5.0
Classifier: Programming Language :: Rust
Classifier: Programming Language :: Python :: Implementation :: CPython
Classifier: Programming Language :: Python :: Implementation :: PyPy
Requires-Dist: pytest >=7.4.4 ; extra == 'dev'
Provides-Extra: dev
License-File: LICENSE
Summary: Bare-minimum binding of deno_core, for embedding JavaScript in Python.
Home-Page: https://github.com/ubolonton/denopy
Author: Tuấn-Anh Nguyễn <ubolonton@gmail.com>
Author-email: Tuấn-Anh Nguyễn <ubolonton@gmail.com>
License: BSD-3-Clause
Requires-Python: >=3.8
